[
    {
        "filename": "/home/u/mike/.config/ssget/MM/ACUSIM/Pres_Poisson/Pres_Poisson.mtx",
        "problem": {
            "id": 1184,
            "group": "ACUSIM",
            "name": "Pres_Poisson",
            "rows": 14822,
            "cols": 14822,
            "nonzeros": 715804,
            "real": true,
            "binary": false,
            "2d3d": true,
            "posdef": true,
            "psym": 1,
            "nsym": 1,
            "kind": "computational fluid dynamics problem",
            "row_distribution": {
                "min": 18,
                "q1": 50.0,
                "median": 50.0,
                "q3": 50.0,
                "max": 50,
                "mean": 48.29334772635272,
                "variance": 26.179228450012638,
                "skewness": -2.997143879449404,
                "kurtosis": 10.879391561663413,
                "hyperskewness": -40.839524286574427,
                "hyperflatness": 160.07912419963268
            },
            "col_distribution": {
                "min": 18,
                "q1": 50.0,
                "median": 50.0,
                "q3": 50.0,
                "max": 50,
                "mean": 48.29334772635272,
                "variance": 26.179228450012638,
                "skewness": -2.997143879449404,
                "kurtosis": 10.879391561663413,
                "hyperskewness": -40.839524286574427,
                "hyperflatness": 160.07912419963268
            }
        },
        "spmv": {
            "coo": {
                "storage": 11452864,
                "time": 32508.8,
                "completed": true
            },
            "csr": {
                "storage": 8648940,
                "time": 30184.4,
                "completed": true
            },
            "ell": {
                "storage": 8893200,
                "time": 59084.8,
                "completed": true
            },
            "sellp": {
                "storage": 8897160,
                "time": 53887.8,
                "completed": true
            },
            "hybrid": {
                "storage": 10622832,
                "time": 43074.4,
                "completed": true
            },
            "hybrid0": {
                "storage": 10385680,
                "time": 45513.1,
                "completed": true
            },
            "hybrid25": {
                "storage": 8893200,
                "time": 62962.3,
                "completed": true
            },
            "hybrid33": {
                "storage": 8893200,
                "time": 62631.0,
                "completed": true
            },
            "hybridlimit0": {
                "storage": 10622832,
                "time": 39693.9,
                "completed": true
            },
            "hybridlimit25": {
                "storage": 10622832,
                "time": 40341.0,
                "completed": true
            },
            "hybridlimit33": {
                "storage": 10622832,
                "time": 39666.4,
                "completed": true
            },
            "hybridminstorage": {
                "storage": 8893200,
                "time": 59164.2,
                "completed": true
            }
        },
        "optimal": {
            "spmv": "csr"
        }
    }
]