[
    {
        "filename": "/home/u/mike/.config/ssget/MM/JGD_Kocay/Trec11/Trec11.mtx",
        "problem": {
            "id": 2145,
            "group": "JGD_Kocay",
            "name": "Trec11",
            "rows": 235,
            "cols": 1138,
            "nonzeros": 35705,
            "real": true,
            "binary": false,
            "2d3d": false,
            "posdef": false,
            "psym": 0,
            "nsym": 0,
            "kind": "combinatorial problem",
            "row_distribution": {
                "min": 5,
                "q1": 109.0,
                "median": 159.0,
                "q3": 198.0,
                "max": 274,
                "mean": 151.93617021276598,
                "variance": 3481.881032141241,
                "skewness": -0.3457989236069326,
                "kurtosis": 2.347403829516236,
                "hyperskewness": -1.9008295912917018,
                "hyperflatness": 7.763846426521798
            },
            "col_distribution": {
                "min": 0,
                "q1": 9.0,
                "median": 18.0,
                "q3": 42.0,
                "max": 179,
                "mean": 31.375219683655538,
                "variance": 1053.9778393629877,
                "skewness": 1.73645634158114,
                "kurtosis": 5.578081854963326,
                "hyperskewness": 16.768117433500728,
                "hyperflatness": 55.29329699096407
            }
        },
        "spmv": {
            "coo": {
                "storage": 571280,
                "time": 18292.9,
                "completed": true
            },
            "csr": {
                "storage": 429404,
                "time": 24851.3,
                "completed": true
            },
            "ell": {
                "storage": 772680,
                "time": 18652.9,
                "completed": true
            },
            "sellp": {
                "storage": 737352,
                "time": 121306.5,
                "completed": true
            },
            "hybrid": {
                "storage": 571280,
                "time": 19801.0,
                "completed": true
            },
            "hybrid0": {
                "storage": 566580,
                "time": 19399.1,
                "completed": true
            },
            "hybrid25": {
                "storage": 504436,
                "time": 26791.4,
                "completed": true
            },
            "hybrid33": {
                "storage": 506608,
                "time": 27448.4,
                "completed": true
            },
            "hybridlimit0": {
                "storage": 571280,
                "time": 25325.7,
                "completed": true
            },
            "hybridlimit25": {
                "storage": 571280,
                "time": 19887.1,
                "completed": true
            },
            "hybridlimit33": {
                "storage": 571280,
                "time": 19984.3,
                "completed": true
            },
            "hybridminstorage": {
                "storage": 504436,
                "time": 22278.9,
                "completed": true
            }
        },
        "optimal": {
            "spmv": "coo"
        }
    }
]